{
    "Monochrome Studio": {
        "followers_count": 31,
        "follows_count": 19,
        "total_media_count": 15,
        "analyzed_posts": 15,
        "total_likes_analyzed": 1928,
        "total_comments_analyzed": 17,
        "average_likes": "128.5",
        "average_comments": "1.1",
        "engagement_rate": "418.280",
        "weekly_posts": "0.00",
        "comments_to_likes_ratio": "0.882",
        "followers_to_follows_ratio": "1.63",
        "updated_at": "2026-04-27T17:50:36.000000Z"
    },
    "Catnip Addict": {
        "followers_count": 70,
        "follows_count": 12,
        "total_media_count": 10,
        "analyzed_posts": 10,
        "total_likes_analyzed": 255,
        "total_comments_analyzed": 6,
        "average_likes": "25.5",
        "average_comments": "0.6",
        "engagement_rate": "37.286",
        "weekly_posts": "0.00",
        "comments_to_likes_ratio": "2.353",
        "followers_to_follows_ratio": "5.83",
        "updated_at": "2026-04-27T17:51:13.000000Z"
    },
    "Playground": {
        "followers_count": 3,
        "follows_count": 1,
        "total_media_count": 6,
        "analyzed_posts": 6,
        "total_likes_analyzed": 8,
        "total_comments_analyzed": 0,
        "average_likes": "1.3",
        "average_comments": "0.0",
        "engagement_rate": "44.444",
        "weekly_posts": "0.00",
        "comments_to_likes_ratio": "0.000",
        "followers_to_follows_ratio": "3.00",
        "updated_at": "2026-04-27T17:51:48.000000Z"
    },
    "Cheerful Studio": {
        "followers_count": 35,
        "follows_count": 4,
        "total_media_count": 4,
        "analyzed_posts": 4,
        "total_likes_analyzed": 76,
        "total_comments_analyzed": 59,
        "average_likes": "19.0",
        "average_comments": "14.8",
        "engagement_rate": "96.429",
        "weekly_posts": "0.00",
        "comments_to_likes_ratio": "77.632",
        "followers_to_follows_ratio": "8.75",
        "updated_at": "2026-04-27T17:52:30.000000Z"
    },
    "ZetaIT": {
        "followers_count": 36,
        "follows_count": 22,
        "total_media_count": 13,
        "analyzed_posts": 13,
        "total_likes_analyzed": 205,
        "total_comments_analyzed": 5,
        "average_likes": "15.8",
        "average_comments": "0.4",
        "engagement_rate": "44.872",
        "weekly_posts": "0.00",
        "comments_to_likes_ratio": "2.439",
        "followers_to_follows_ratio": "1.64",
        "updated_at": "2026-04-27T17:53:23.000000Z"
    },
    "Artificail Idiots": {
        "followers_count": 14,
        "follows_count": 21,
        "total_media_count": 5,
        "analyzed_posts": 5,
        "total_likes_analyzed": 67,
        "total_comments_analyzed": 5,
        "average_likes": "13.4",
        "average_comments": "1.0",
        "engagement_rate": "102.857",
        "weekly_posts": "0.00",
        "comments_to_likes_ratio": "7.463",
        "followers_to_follows_ratio": "0.67",
        "updated_at": "2026-04-27T17:53:55.000000Z"
    },
    "PJTeam": {
        "followers_count": 34,
        "follows_count": 20,
        "total_media_count": 38,
        "analyzed_posts": 30,
        "total_likes_analyzed": 268,
        "total_comments_analyzed": 6,
        "average_likes": "8.9",
        "average_comments": "0.2",
        "engagement_rate": "26.863",
        "weekly_posts": "0.00",
        "comments_to_likes_ratio": "2.239",
        "followers_to_follows_ratio": "1.70",
        "updated_at": "2026-04-27T17:54:58.000000Z"
    },
    "St. Barbara Studio's": {
        "followers_count": 36,
        "follows_count": 8,
        "total_media_count": 1,
        "analyzed_posts": 1,
        "total_likes_analyzed": 51,
        "total_comments_analyzed": 0,
        "average_likes": "51.0",
        "average_comments": "0.0",
        "engagement_rate": "141.667",
        "weekly_posts": "0.00",
        "comments_to_likes_ratio": "0.000",
        "followers_to_follows_ratio": "4.50",
        "updated_at": "2026-04-27T17:55:37.000000Z"
    },
    "Table Entertainment": {
        "followers_count": 15,
        "follows_count": 5,
        "total_media_count": 6,
        "analyzed_posts": 6,
        "total_likes_analyzed": 62,
        "total_comments_analyzed": 9,
        "average_likes": "10.3",
        "average_comments": "1.5",
        "engagement_rate": "78.889",
        "weekly_posts": "0.00",
        "comments_to_likes_ratio": "14.516",
        "followers_to_follows_ratio": "3.00",
        "updated_at": "2026-04-27T17:56:13.000000Z"
    },
    "Mechan": {
        "followers_count": 26,
        "follows_count": 0,
        "total_media_count": 2,
        "analyzed_posts": 2,
        "total_likes_analyzed": 22,
        "total_comments_analyzed": 2,
        "average_likes": "11.0",
        "average_comments": "1.0",
        "engagement_rate": "46.154",
        "weekly_posts": "0.00",
        "comments_to_likes_ratio": "9.091",
        "followers_to_follows_ratio": "0.00",
        "updated_at": "2026-04-27T17:56:51.000000Z"
    },
    "Polar Bears Inc.": {
        "followers_count": 92,
        "follows_count": 52,
        "total_media_count": 37,
        "analyzed_posts": 30,
        "total_likes_analyzed": 723,
        "total_comments_analyzed": 35,
        "average_likes": "24.1",
        "average_comments": "1.2",
        "engagement_rate": "27.464",
        "weekly_posts": "0.00",
        "comments_to_likes_ratio": "4.841",
        "followers_to_follows_ratio": "1.77",
        "updated_at": "2026-04-27T17:57:59.000000Z"
    },
    "Knedle": {
        "followers_count": 47,
        "follows_count": 3,
        "total_media_count": 18,
        "analyzed_posts": 18,
        "total_likes_analyzed": 377,
        "total_comments_analyzed": 4,
        "average_likes": "20.9",
        "average_comments": "0.2",
        "engagement_rate": "45.035",
        "weekly_posts": "0.00",
        "comments_to_likes_ratio": "1.061",
        "followers_to_follows_ratio": "15.67",
        "updated_at": "2026-04-27T17:58:41.000000Z"
    },
    "Stokrotki": {
        "followers_count": 31,
        "follows_count": 10,
        "total_media_count": 18,
        "analyzed_posts": 18,
        "total_likes_analyzed": 247,
        "total_comments_analyzed": 26,
        "average_likes": "13.7",
        "average_comments": "1.4",
        "engagement_rate": "48.925",
        "weekly_posts": "0.00",
        "comments_to_likes_ratio": "10.526",
        "followers_to_follows_ratio": "3.10",
        "updated_at": "2026-04-27T17:59:23.000000Z"
    },
    "Fundacja Teatrikon": {
        "followers_count": 799,
        "follows_count": 29,
        "total_media_count": 500,
        "analyzed_posts": 30,
        "total_likes_analyzed": 1233,
        "total_comments_analyzed": 149,
        "average_likes": "41.1",
        "average_comments": "5.0",
        "engagement_rate": "5.766",
        "weekly_posts": "0.00",
        "comments_to_likes_ratio": "12.084",
        "followers_to_follows_ratio": "27.55",
        "updated_at": "2026-04-27T18:00:30.000000Z"
    },
    "Żegluga za Komputerem": {
        "followers_count": 59,
        "follows_count": 14,
        "total_media_count": 12,
        "analyzed_posts": 12,
        "total_likes_analyzed": 360,
        "total_comments_analyzed": 22,
        "average_likes": "30.0",
        "average_comments": "1.8",
        "engagement_rate": "53.955",
        "weekly_posts": "0.00",
        "comments_to_likes_ratio": "6.111",
        "followers_to_follows_ratio": "4.21",
        "updated_at": "2026-04-27T18:01:14.000000Z"
    },
    "Cockroach Pulp Games": {
        "followers_count": 19,
        "follows_count": 6,
        "total_media_count": 13,
        "analyzed_posts": 13,
        "total_likes_analyzed": 111,
        "total_comments_analyzed": 14,
        "average_likes": "8.5",
        "average_comments": "1.1",
        "engagement_rate": "50.607",
        "weekly_posts": "0.00",
        "comments_to_likes_ratio": "12.613",
        "followers_to_follows_ratio": "3.17",
        "updated_at": "2026-04-27T18:01:53.000000Z"
    },
    "MechaKoty": {
        "followers_count": 24,
        "follows_count": 13,
        "total_media_count": 5,
        "analyzed_posts": 5,
        "total_likes_analyzed": 51,
        "total_comments_analyzed": 2,
        "average_likes": "10.2",
        "average_comments": "0.4",
        "engagement_rate": "44.167",
        "weekly_posts": "0.00",
        "comments_to_likes_ratio": "3.922",
        "followers_to_follows_ratio": "1.85",
        "updated_at": "2026-04-27T18:02:35.000000Z"
    },
    "FC Royal Mońki": {
        "followers_count": 6,
        "follows_count": 4,
        "total_media_count": 2,
        "analyzed_posts": 2,
        "total_likes_analyzed": 4,
        "total_comments_analyzed": 0,
        "average_likes": "2.0",
        "average_comments": "0.0",
        "engagement_rate": "33.333",
        "weekly_posts": "0.00",
        "comments_to_likes_ratio": "0.000",
        "followers_to_follows_ratio": "1.50",
        "updated_at": "2026-04-27T18:03:08.000000Z"
    },
    "Elektryk Entertainment": {
        "followers_count": 39,
        "follows_count": 20,
        "total_media_count": 3,
        "analyzed_posts": 3,
        "total_likes_analyzed": 63,
        "total_comments_analyzed": 3,
        "average_likes": "21.0",
        "average_comments": "1.0",
        "engagement_rate": "56.410",
        "weekly_posts": "0.00",
        "comments_to_likes_ratio": "4.762",
        "followers_to_follows_ratio": "1.95",
        "updated_at": "2026-04-27T18:03:53.000000Z"
    },
    "Dark District": {
        "followers_count": 36,
        "follows_count": 5,
        "total_media_count": 20,
        "analyzed_posts": 20,
        "total_likes_analyzed": 133,
        "total_comments_analyzed": 4,
        "average_likes": "6.7",
        "average_comments": "0.2",
        "engagement_rate": "19.028",
        "weekly_posts": "0.00",
        "comments_to_likes_ratio": "3.008",
        "followers_to_follows_ratio": "7.20",
        "updated_at": "2026-04-27T18:04:44.000000Z"
    },
    "Komornicy": {
        "followers_count": 43,
        "follows_count": 13,
        "total_media_count": 24,
        "analyzed_posts": 24,
        "total_likes_analyzed": 417,
        "total_comments_analyzed": 13,
        "average_likes": "17.4",
        "average_comments": "0.5",
        "engagement_rate": "41.667",
        "weekly_posts": "0.00",
        "comments_to_likes_ratio": "3.118",
        "followers_to_follows_ratio": "3.31",
        "updated_at": "2026-04-27T18:05:33.000000Z"
    },
    "Getaway Games": {
        "followers_count": 79,
        "follows_count": 2,
        "total_media_count": 7,
        "analyzed_posts": 7,
        "total_likes_analyzed": 248,
        "total_comments_analyzed": 23,
        "average_likes": "35.4",
        "average_comments": "3.3",
        "engagement_rate": "49.005",
        "weekly_posts": "0.00",
        "comments_to_likes_ratio": "9.274",
        "followers_to_follows_ratio": "39.50",
        "updated_at": "2026-04-27T18:06:05.000000Z"
    },
    "Alotis": {
        "followers_count": 10,
        "follows_count": 0,
        "total_media_count": 1,
        "analyzed_posts": 1,
        "total_likes_analyzed": 7,
        "total_comments_analyzed": 3,
        "average_likes": "7.0",
        "average_comments": "3.0",
        "engagement_rate": "100.000",
        "weekly_posts": "0.00",
        "comments_to_likes_ratio": "42.857",
        "followers_to_follows_ratio": "0.00",
        "updated_at": "2026-04-27T18:06:43.000000Z"
    },
    "Turniej Trójgamiczny": {
        "followers_count": 260,
        "follows_count": 80,
        "total_media_count": 86,
        "analyzed_posts": 30,
        "total_likes_analyzed": 651,
        "total_comments_analyzed": 11,
        "average_likes": "21.7",
        "average_comments": "0.4",
        "engagement_rate": "8.487",
        "weekly_posts": "0.00",
        "comments_to_likes_ratio": "1.690",
        "followers_to_follows_ratio": "3.25",
        "updated_at": "2026-04-27T18:07:51.000000Z"
    },
    "PixelFlower": {
        "followers_count": 16,
        "follows_count": 5,
        "total_media_count": 4,
        "analyzed_posts": 4,
        "total_likes_analyzed": 41,
        "total_comments_analyzed": 3,
        "average_likes": "10.2",
        "average_comments": "0.8",
        "engagement_rate": "68.750",
        "weekly_posts": "0.00",
        "comments_to_likes_ratio": "7.317",
        "followers_to_follows_ratio": "3.20",
        "updated_at": "2026-04-27T18:08:23.000000Z"
    },
    "BronkDEV": {
        "followers_count": 32,
        "follows_count": 23,
        "total_media_count": 19,
        "analyzed_posts": 19,
        "total_likes_analyzed": 115,
        "total_comments_analyzed": 8,
        "average_likes": "6.1",
        "average_comments": "0.4",
        "engagement_rate": "20.230",
        "weekly_posts": "0.00",
        "comments_to_likes_ratio": "6.957",
        "followers_to_follows_ratio": "1.39",
        "updated_at": "2026-04-27T18:09:05.000000Z"
    },
    "JVELK": {
        "followers_count": 229,
        "follows_count": 12,
        "total_media_count": 40,
        "analyzed_posts": 30,
        "total_likes_analyzed": 2396,
        "total_comments_analyzed": 49,
        "average_likes": "79.9",
        "average_comments": "1.6",
        "engagement_rate": "35.590",
        "weekly_posts": "0.00",
        "comments_to_likes_ratio": "2.045",
        "followers_to_follows_ratio": "19.08",
        "updated_at": "2026-04-27T18:10:09.000000Z"
    }
}